permapy/__init__.py
permapy/arweave_client.py
permapy/async_client.py
permapy/permaweb.py
permapy/transactions.py
permapy/utils.py
permapy/wallet.py
permapy-0.1.0.dist-info/METADATA
permapy-0.1.0.dist-info/WHEEL
permapy-0.1.0.dist-info/top_level.txt
permapy-0.1.0.dist-info/RECORD
