Metadata-Version: 2.1
Name: permapy
Version: 0.1.0
Summary: A Python package to interact with the Arweave network and Permaweb
Home-page: https://github.com/krishvsoni
Author: Krish Soni
Classifier: Programming Language :: Python :: 3
Classifier: License :: OSI Approved :: MIT License
Classifier: Operating System :: OS Independent
Requires-Python: >=3.6
Requires-Dist: requests
Requires-Dist: aiohttp
